{
  "duration": null,
  "segments": [
    {
      "id": "seg_0",
      "end": 0.55,
      "speaker": "agent",
      "start": 0.0,
      "text": " Wohl guten Tag.",
      "type": "transcript.text.segment"
    },
    {
      "id": "seg_1",
      "end": 2.2,
      "speaker": "A",
      "start": 0.7,
      "text": " Ja, Benedikt, guten Tag.",
      "type": "transcript.text.segment"
    },
    {
      "id": "seg_2",
      "end": 3.55,
      "speaker": "A",
      "start": 2.3499999999999996,
      "text": " Ich habe eine Frage.",
      "type": "transcript.text.segment"
    },
    {
      "id": "seg_3",
      "end": 7.55,
      "speaker": "A",
      "start": 3.6499999999999995,
      "text": " Ich brauche eine Beglaubigung für ein Zeugnis.",
      "type": "transcript.text.segment"
    },
    {
      "id": "seg_4",
      "end": 8.9,
      "speaker": "agent",
      "start": 8.75,
      "text": " Ja.",
      "type": "transcript.text.segment"
    },
    {
      "id": "seg_5",
      "end": 10.5,
      "speaker": "A",
      "start": 8.9,
      "text": " Wo muss ich mich dahin wenden?",
      "type": "transcript.text.segment"
    },
    {
      "id": "seg_6",
      "end": 13.0,
      "speaker": "agent",
      "start": 10.95,
      "text": " Sind Sie im Bürgerbüro richtig?",
      "type": "transcript.text.segment"
    },
    {
      "id": "seg_7",
      "end": 14.3,
      "speaker": "A",
      "start": 13.25,
      "text": " Ja, okay.",
      "type": "transcript.text.segment"
    },
    {
      "id": "seg_8",
      "end": 18.05,
      "speaker": "agent",
      "start": 15.05,
      "text": " Jetzt muss ich bloß gerade geschwind gucken.",
      "type": "transcript.text.segment"
    },
    {
      "id": "seg_9",
      "end": 25.85,
      "speaker": "A",
      "start": 22.75,
      "text": " Ich war nicht sicher, Standesamt oder Bürgerbüro.",
      "type": "transcript.text.segment"
    },
    {
      "id": "seg_10",
      "end": 28.282,
      "speaker": "agent",
      "start": 27.732,
      "text": " Ja, gut,",
      "type": "transcript.text.segment"
    },
    {
      "id": "seg_11",
      "end": 33.832,
      "speaker": "agent",
      "start": 28.381999999999998,
      "text": " ich wollte ja kein neues Dokument ausgestellt haben vom Staatsamt. Sie bringen Ihr Dokumente mit?",
      "type": "transcript.text.segment"
    },
    {
      "id": "seg_12",
      "end": 36.882,
      "speaker": "A",
      "start": 35.282,
      "text": " Das ist nur ein Zeugnis,",
      "type": "transcript.text.segment"
    },
    {
      "id": "seg_13",
      "end": 37.082,
      "speaker": "A",
      "start": 36.932,
      "text": " ja,",
      "type": "transcript.text.segment"
    },
    {
      "id": "seg_14",
      "end": 40.582,
      "speaker": "A",
      "start": 37.182,
      "text": " und dass dabei eine beglaubigte Abschrift oder wie das heißt.",
      "type": "transcript.text.segment"
    },
    {
      "id": "seg_15",
      "end": 44.682,
      "speaker": "agent",
      "start": 40.832,
      "text": " Ja, da bräuchte man aber einen Termin.",
      "type": "transcript.text.segment"
    },
    {
      "id": "seg_16",
      "end": 51.084,
      "speaker": "agent",
      "start": 48.884,
      "text": " Ich muss ja heute immer gucken, heute ist voll.",
      "type": "transcript.text.segment"
    },
    {
      "id": "seg_17",
      "end": 57.734,
      "speaker": "agent",
      "start": 52.234,
      "text": " Wir haben jeden Tag eigentlich noch freie Termine, bloß sehe ich die auch erst wie Sie morgen um 8 Uhr.",
      "type": "transcript.text.segment"
    },
    {
      "id": "seg_18",
      "end": 59.184000000000005,
      "speaker": "A",
      "start": 58.634,
      "text": " Aha, okay.",
      "type": "transcript.text.segment"
    },
    {
      "id": "seg_19",
      "end": 63.534000000000006,
      "speaker": "agent",
      "start": 60.684000000000005,
      "text": " Entweder Sie rufen morgen um 8 Uhr nochmal an am Tag,",
      "type": "transcript.text.segment"
    },
    {
      "id": "seg_20",
      "end": 64.284,
      "speaker": "agent",
      "start": 63.634,
      "text": " wo Sie können,",
      "type": "transcript.text.segment"
    },
    {
      "id": "seg_21",
      "end": 65.084,
      "speaker": "agent",
      "start": 64.434,
      "text": " wo Sie wissen,",
      "type": "transcript.text.segment"
    },
    {
      "id": "seg_22",
      "end": 67.634,
      "speaker": "agent",
      "start": 65.134,
      "text": " oder Sie gucken online.",
      "type": "transcript.text.segment"
    },
    {
      "id": "seg_23",
      "end": 74.634,
      "speaker": "agent",
      "start": 67.884,
      "text": " Wir haben unsere Homepage Stadtneckersulm und da gibt es eine Online-Terminvergabe. Wenn wir da heute...",
      "type": "transcript.text.segment"
    },
    {
      "id": "seg_24",
      "end": 74.834,
      "speaker": "A",
      "start": 74.634,
      "text": " Okay.",
      "type": "transcript.text.segment"
    },
    {
      "id": "seg_25",
      "end": 80.208,
      "speaker": "agent",
      "start": 75.508,
      "text": " Um 8 Uhr sich einloggt, kriegt man da auch drüber einen Termin, also wie sie möchte.",
      "type": "transcript.text.segment"
    },
    {
      "id": "seg_26",
      "end": 81.258,
      "speaker": "A",
      "start": 80.55799999999999,
      "text": " Okay,",
      "type": "transcript.text.segment"
    },
    {
      "id": "seg_27",
      "end": 81.30799999999999,
      "speaker": "agent",
      "start": 81.258,
      "text": " Ja?",
      "type": "transcript.text.segment"
    },
    {
      "id": "seg_28",
      "end": 81.80799999999999,
      "speaker": "A",
      "start": 81.30799999999999,
      "text": " okay,",
      "type": "transcript.text.segment"
    },
    {
      "id": "seg_29",
      "end": 86.108,
      "speaker": "A",
      "start": 81.958,
      "text": " ja, weiß ich Bescheid. Gut, aber ich weiß erstmal, auf welches Amt ich muss.",
      "type": "transcript.text.segment"
    },
    {
      "id": "seg_30",
      "end": 86.608,
      "speaker": "agent",
      "start": 86.108,
      "text": " Ja,",
      "type": "transcript.text.segment"
    },
    {
      "id": "seg_31",
      "end": 87.458,
      "speaker": "agent",
      "start": 86.708,
      "text": " wo sie hin muss,",
      "type": "transcript.text.segment"
    },
    {
      "id": "seg_32",
      "end": 87.80799999999999,
      "speaker": "agent",
      "start": 87.508,
      "text": " genau.",
      "type": "transcript.text.segment"
    },
    {
      "id": "seg_33",
      "end": 88.55799999999999,
      "speaker": "A",
      "start": 88.05799999999999,
      "text": " Richtig,",
      "type": "transcript.text.segment"
    },
    {
      "id": "seg_34",
      "end": 89.758,
      "speaker": "A",
      "start": 88.708,
      "text": " dann alles klar,",
      "type": "transcript.text.segment"
    },
    {
      "id": "seg_35",
      "end": 90.258,
      "speaker": "A",
      "start": 89.908,
      "text": " Dankeschön.",
      "type": "transcript.text.segment"
    },
    {
      "id": "seg_36",
      "end": 91.30799999999999,
      "speaker": "agent",
      "start": 90.258,
      "text": " Okay, bitteschön,",
      "type": "transcript.text.segment"
    },
    {
      "id": "seg_37",
      "end": 91.508,
      "speaker": "A",
      "start": 91.30799999999999,
      "text": " Ihnen",
      "type": "transcript.text.segment"
    },
    {
      "id": "seg_38",
      "end": 91.80799999999999,
      "speaker": "agent",
      "start": 91.508,
      "text": " Wochenende,",
      "type": "transcript.text.segment"
    },
    {
      "id": "seg_39",
      "end": 92.208,
      "speaker": "A",
      "start": 91.80799999999999,
      "text": " auch,",
      "type": "transcript.text.segment"
    },
    {
      "id": "seg_40",
      "end": 92.658,
      "speaker": "agent",
      "start": 92.208,
      "text": " bitte.",
      "type": "transcript.text.segment"
    },
    {
      "id": "seg_41",
      "end": 93.008,
      "speaker": "A",
      "start": 92.658,
      "text": " danke.",
      "type": "transcript.text.segment"
    },
    {
      "id": "seg_42",
      "end": 93.708,
      "speaker": "A",
      "start": 93.258,
      "text": " Tschüss.",
      "type": "transcript.text.segment"
    }
  ],
  "task": null,
  "text": "Wohl guten Tag. Ja, Benedikt, guten Tag. Ich habe eine Frage. Ich brauche eine Beglaubigung für ein Zeugnis. Ja. Wo muss ich mich dahin wenden? Sind Sie im Bürgerbüro richtig? Ja, okay. Jetzt muss ich bloß gerade geschwind gucken. Ich war nicht sicher, Standesamt oder Bürgerbüro.\nJa, gut, ich wollte ja kein neues Dokument ausgestellt haben vom Staatsamt. Sie bringen Ihr Dokumente mit? Das ist nur ein Zeugnis, ja, und dass dabei eine beglaubigte Abschrift oder wie das heißt. Ja, da bräuchte man aber einen Termin.\nIch muss ja heute immer gucken, heute ist voll. Wir haben jeden Tag eigentlich noch freie Termine, bloß sehe ich die auch erst wie Sie morgen um 8 Uhr. Aha, okay. Entweder Sie rufen morgen um 8 Uhr nochmal an am Tag, wo Sie können, wo Sie wissen, oder Sie gucken online. Wir haben unsere Homepage Stadtneckersulm und da gibt es eine Online-Terminvergabe. Wenn wir da heute... Okay.\nUm 8 Uhr sich einloggt, kriegt man da auch drüber einen Termin, also wie sie möchte. Okay, Ja? okay, ja, weiß ich Bescheid. Gut, aber ich weiß erstmal, auf welches Amt ich muss. Ja, wo sie hin muss, genau. Richtig, dann alles klar, Dankeschön. Okay, bitteschön, Ihnen Wochenende, auch, bitte. danke. Tschüss.",
  "usage": {
    "input_tokens": 1478,
    "output_tokens": 2904,
    "total_tokens": 4382,
    "type": "tokens",
    "input_token_details": {
      "audio_tokens": 1395,
      "text_tokens": 83
    }
  }
}