{
  "duration": null,
  "segments": [
    {
      "id": "seg_0",
      "end": 1.3499999999999999,
      "speaker": "agent",
      "start": 0.0,
      "text": " Vielleicht wollen Sie heute Guten Tag.",
      "type": "transcript.text.segment"
    },
    {
      "id": "seg_1",
      "end": 3.8999999999999995,
      "speaker": "A",
      "start": 1.95,
      "text": " Mehr als Stadtbahn, wem von guten Tag.",
      "type": "transcript.text.segment"
    },
    {
      "id": "seg_2",
      "end": 7.599999999999999,
      "speaker": "A",
      "start": 3.999999999999999,
      "text": " Ich bin bei uns Integrationsbeauftragte.",
      "type": "transcript.text.segment"
    },
    {
      "id": "seg_3",
      "end": 10.7,
      "speaker": "A",
      "start": 7.799999999999998,
      "text": " Folgendes. Mich hat kurz vor zwölf gestern eine Dame,",
      "type": "transcript.text.segment"
    },
    {
      "id": "seg_4",
      "end": 17.799999999999997,
      "speaker": "A",
      "start": 10.85,
      "text": " hat sich gesagt, Integrationsbeauftragte. Jetzt habe ich festgestellt, die Frau Bruns, die ist gar nicht da.",
      "type": "transcript.text.segment"
    },
    {
      "id": "seg_5",
      "end": 20.15,
      "speaker": "A",
      "start": 18.349999999999998,
      "text": " Haben Sie da noch jemand anderen?",
      "type": "transcript.text.segment"
    },
    {
      "id": "seg_6",
      "end": 22.2,
      "speaker": "agent",
      "start": 21.099999999999998,
      "text": " Ja, kleinen",
      "type": "transcript.text.segment"
    },
    {
      "id": "seg_7",
      "end": 22.55,
      "speaker": "A",
      "start": 22.2,
      "text": " Sie sprach",
      "type": "transcript.text.segment"
    },
    {
      "id": "seg_8",
      "end": 23.05,
      "speaker": "agent",
      "start": 22.55,
      "text": " Moment.",
      "type": "transcript.text.segment"
    },
    {
      "id": "seg_9",
      "end": 24.400000000000002,
      "speaker": "A",
      "start": 23.05,
      "text": " mit starkem Akzent.",
      "type": "transcript.text.segment"
    },
    {
      "id": "seg_10",
      "end": 25.892,
      "speaker": "agent",
      "start": 25.492,
      "text": " Ja,",
      "type": "transcript.text.segment"
    },
    {
      "id": "seg_11",
      "end": 27.342000000000002,
      "speaker": "agent",
      "start": 26.042,
      "text": " jetzt",
      "type": "transcript.text.segment"
    },
    {
      "id": "seg_12",
      "end": 40.992000000000004,
      "speaker": "agent",
      "start": 38.942,
      "text": " habe ich sie nicht da drin.",
      "type": "transcript.text.segment"
    },
    {
      "id": "seg_13",
      "end": 53.916,
      "speaker": "agent",
      "start": 52.916,
      "text": " Eine Frau Ulga,",
      "type": "transcript.text.segment"
    },
    {
      "id": "seg_14",
      "end": 55.565999999999995,
      "speaker": "agent",
      "start": 54.016,
      "text": " ihres Mannes, können Sie.",
      "type": "transcript.text.segment"
    },
    {
      "id": "seg_15",
      "end": 57.965999999999994,
      "speaker": "A",
      "start": 55.866,
      "text": " Ja, die hat so kurz vor zwölf angerufen.",
      "type": "transcript.text.segment"
    },
    {
      "id": "seg_16",
      "end": 61.916,
      "speaker": "A",
      "start": 58.016,
      "text": " Wir mussten dann auch noch den Server runterfahren, weil da was eingestellt wurde.",
      "type": "transcript.text.segment"
    },
    {
      "id": "seg_17",
      "end": 63.816,
      "speaker": "A",
      "start": 62.016,
      "text": " Und dann war sie weg.",
      "type": "transcript.text.segment"
    },
    {
      "id": "seg_18",
      "end": 64.816,
      "speaker": "A",
      "start": 63.916,
      "text": " Ich konnte die Information,",
      "type": "transcript.text.segment"
    },
    {
      "id": "seg_19",
      "end": 65.966,
      "speaker": "A",
      "start": 65.066,
      "text": " die brauche ich nicht kriegen.",
      "type": "transcript.text.segment"
    },
    {
      "id": "seg_20",
      "end": 68.816,
      "speaker": "agent",
      "start": 66.366,
      "text": " Ich verbinde Sie, versuche Sie mal schön weiterzumachen.",
      "type": "transcript.text.segment"
    }
  ],
  "task": null,
  "text": "Vielleicht wollen Sie heute Guten Tag. Mehr als Stadtbahn, wem von guten Tag. Ich bin bei uns Integrationsbeauftragte. Folgendes. Mich hat kurz vor zwölf gestern eine Dame, hat sich gesagt, Integrationsbeauftragte. Jetzt habe ich festgestellt, die Frau Bruns, die ist gar nicht da. Haben Sie da noch jemand anderen? Ja, kleinen Sie sprach Moment. mit starkem Akzent.\nJa, jetzt habe ich sie nicht da drin.\nEine Frau Ulga, ihres Mannes, können Sie. Ja, die hat so kurz vor zwölf angerufen. Wir mussten dann auch noch den Server runterfahren, weil da was eingestellt wurde. Und dann war sie weg. Ich konnte die Information, die brauche ich nicht kriegen. Ich verbinde Sie, versuche Sie mal schön weiterzumachen.",
  "usage": {
    "input_tokens": 1044,
    "output_tokens": 1794,
    "total_tokens": 2838,
    "type": "tokens",
    "input_token_details": {
      "audio_tokens": 984,
      "text_tokens": 60
    }
  }
}