{
  "duration": null,
  "segments": [
    {
      "id": "seg_0",
      "end": 0.95,
      "speaker": "A",
      "start": 0.0,
      "text": " Grüß Gott, guten Tag.",
      "type": "transcript.text.segment"
    },
    {
      "id": "seg_1",
      "end": 6.75,
      "speaker": "B",
      "start": 1.3499999999999999,
      "text": " Guten Tag, mein Name ist Hermann. Ich bräuchte Meldebescheinigung. Mein Arbeitgeber bräuchte die.",
      "type": "transcript.text.segment"
    },
    {
      "id": "seg_2",
      "end": 17.000000000000004,
      "speaker": "A",
      "start": 7.3999999999999995,
      "text": " Ja, steht da irgendein Aktzeichen drauf, dann bringen Sie den Beleg mit, dass man das mit eintippe an, sonst steht kein Termin für unsere Öffnungszeiten hier vorbeikommen.",
      "type": "transcript.text.segment"
    },
    {
      "id": "seg_3",
      "end": 20.07,
      "speaker": "B",
      "start": 17.62,
      "text": " Okay, können Sie mir das nicht zuschicken per E-Mail?",
      "type": "transcript.text.segment"
    },
    {
      "id": "seg_4",
      "end": 27.37,
      "speaker": "B",
      "start": 20.67,
      "text": " Weil ich bin seit drei Jahren bei Ihnen gemeldet. Können Sie mir das nicht per E-Mail zuschicken?",
      "type": "transcript.text.segment"
    },
    {
      "id": "seg_5",
      "end": 27.82,
      "speaker": "A",
      "start": 27.42,
      "text": " Nee,",
      "type": "transcript.text.segment"
    },
    {
      "id": "seg_6",
      "end": 28.020000000000003,
      "speaker": "B",
      "start": 27.82,
      "text": " Zu",
      "type": "transcript.text.segment"
    },
    {
      "id": "seg_7",
      "end": 30.12,
      "speaker": "A",
      "start": 28.020000000000003,
      "text": " sie muss eigentlich persönlich kommen,",
      "type": "transcript.text.segment"
    },
    {
      "id": "seg_8",
      "end": 32.32,
      "speaker": "B",
      "start": 31.72,
      "text": " Okay.",
      "type": "transcript.text.segment"
    },
    {
      "id": "seg_9",
      "end": 38.07,
      "speaker": "A",
      "start": 33.269999999999996,
      "text": " war dieses Quokkarton noch einmal, also so viel ich weiß.",
      "type": "transcript.text.segment"
    },
    {
      "id": "seg_10",
      "end": 52.178000000000004,
      "speaker": "A",
      "start": 50.228,
      "text": " Ja, nette Stimme persönlich kommen,",
      "type": "transcript.text.segment"
    },
    {
      "id": "seg_11",
      "end": 54.178,
      "speaker": "A",
      "start": 52.228,
      "text": " aber halt ohne Termin.",
      "type": "transcript.text.segment"
    },
    {
      "id": "seg_12",
      "end": 56.028,
      "speaker": "A",
      "start": 55.728,
      "text": " Ja,",
      "type": "transcript.text.segment"
    },
    {
      "id": "seg_13",
      "end": 56.228,
      "speaker": "B",
      "start": 56.028,
      "text": " Okay,",
      "type": "transcript.text.segment"
    },
    {
      "id": "seg_14",
      "end": 59.028000000000006,
      "speaker": "A",
      "start": 56.228,
      "text": " sich einfach vorne an der Infotheke bei uns melden.",
      "type": "transcript.text.segment"
    },
    {
      "id": "seg_15",
      "end": 62.078,
      "speaker": "A",
      "start": 61.528000000000006,
      "text": " Ja,",
      "type": "transcript.text.segment"
    },
    {
      "id": "seg_16",
      "end": 63.878,
      "speaker": "A",
      "start": 62.128,
      "text": " wir haben heute bis 17 Uhr, nur so.",
      "type": "transcript.text.segment"
    },
    {
      "id": "seg_17",
      "end": 64.97800000000001,
      "speaker": "B",
      "start": 63.878,
      "text": " Ja, das geht heute nicht.",
      "type": "transcript.text.segment"
    },
    {
      "id": "seg_18",
      "end": 65.078,
      "speaker": "A",
      "start": 64.97800000000001,
      "text": " Ja,",
      "type": "transcript.text.segment"
    },
    {
      "id": "seg_19",
      "end": 65.578,
      "speaker": "B",
      "start": 65.078,
      "text": " Ja, okay,",
      "type": "transcript.text.segment"
    },
    {
      "id": "seg_20",
      "end": 65.678,
      "speaker": "A",
      "start": 65.578,
      "text": " okay,",
      "type": "transcript.text.segment"
    },
    {
      "id": "seg_21",
      "end": 66.028,
      "speaker": "B",
      "start": 65.678,
      "text": " danke schön.",
      "type": "transcript.text.segment"
    },
    {
      "id": "seg_22",
      "end": 67.078,
      "speaker": "A",
      "start": 66.028,
      "text": " kein Problem,",
      "type": "transcript.text.segment"
    },
    {
      "id": "seg_23",
      "end": 67.578,
      "speaker": "A",
      "start": 67.278,
      "text": " tschüss.",
      "type": "transcript.text.segment"
    }
  ],
  "task": null,
  "text": "Grüß Gott, guten Tag. Guten Tag, mein Name ist Hermann. Ich bräuchte Meldebescheinigung. Mein Arbeitgeber bräuchte die. Ja, steht da irgendein Aktzeichen drauf, dann bringen Sie den Beleg mit, dass man das mit eintippe an, sonst steht kein Termin für unsere Öffnungszeiten hier vorbeikommen.\nOkay, können Sie mir das nicht zuschicken per E -Mail? Weil ich bin seit drei Jahren bei Ihnen gemeldet. Können Sie mir das nicht per E-Mail zuschicken? Nee, Zu sie muss eigentlich persönlich kommen, Okay. war dieses Quokkarton noch einmal, also so viel ich weiß.\nJa, nette Stimme persönlich kommen, aber halt ohne Termin. Ja, Okay, sich einfach vorne an der Infotheke bei uns melden. Ja, wir haben heute bis 17 Uhr, nur so. Ja, das geht heute nicht. Ja, Ja, okay, okay, danke schön. kein Problem, tschüss.",
  "usage": {
    "input_tokens": 922,
    "output_tokens": 1784,
    "total_tokens": 2706,
    "type": "tokens",
    "input_token_details": {
      "audio_tokens": 874,
      "text_tokens": 48
    }
  }
}